deepsquads_customization/__init__.py
deepsquads_customization/addons.py
deepsquads_customization/checks.py
deepsquads_customization/models.py
deepsquads_customization-0.1.dist-info/COPYING
deepsquads_customization-0.1.dist-info/METADATA
deepsquads_customization-0.1.dist-info/WHEEL
deepsquads_customization-0.1.dist-info/top_level.txt
deepsquads_customization-0.1.dist-info/RECORD
